pnu_portstreelint-1.4.2.data/data/share/man/man8/portstreelint.8.gz
portstreelint/__init__.py
portstreelint/check_categories.py
portstreelint/check_comment.py
portstreelint/check_description_file.py
portstreelint/check_installation_prefix.py
portstreelint/check_licenses.py
portstreelint/check_maintainer.py
portstreelint/check_marks.py
portstreelint/check_plist.py
portstreelint/check_port_path.py
portstreelint/check_unchanging_ports.py
portstreelint/check_vulnerabilities.py
portstreelint/check_www_site.py
portstreelint/library.py
portstreelint/load_config.py
portstreelint/load_data.py
portstreelint/main.py
portstreelint/show_categories.py
portstreelint/show_maintainers.py
portstreelint/show_notifications.py
portstreelint/show_summary.py
pnu_portstreelint-1.4.2.dist-info/License
pnu_portstreelint-1.4.2.dist-info/METADATA
pnu_portstreelint-1.4.2.dist-info/WHEEL
pnu_portstreelint-1.4.2.dist-info/entry_points.txt
pnu_portstreelint-1.4.2.dist-info/top_level.txt
pnu_portstreelint-1.4.2.dist-info/RECORD
