Metadata-Version: 2.1
Name: pnu-portstreelint
Version: 1.4.2
Summary: FreeBSD ports tree lint
Home-page: https://github.com/HubTou/portstreelint/
Author: Hubert Tournier
Author-email: hubert.tournier@gmail.com
License: BSD 3-Clause License
Project-URL: Bug Tracker, https://github.com/HubTou/portstreelint/issues
Keywords: pnu-project
Classifier: Development Status :: 5 - Production/Stable
Classifier: Environment :: Console
Classifier: Intended Audience :: Developers
Classifier: Intended Audience :: System Administrators
Classifier: License :: OSI Approved :: BSD License
Classifier: Natural Language :: English
Classifier: Operating System :: POSIX :: BSD :: FreeBSD
Classifier: Programming Language :: Python :: 3.6
Classifier: Programming Language :: Python :: 3.7
Classifier: Programming Language :: Python :: 3.8
Classifier: Programming Language :: Python :: 3.9
Classifier: Programming Language :: Python :: 3.10
Classifier: Programming Language :: Python :: 3.11
Classifier: Programming Language :: Python :: 3.12
Classifier: Topic :: System
Classifier: Topic :: Utilities
Requires-Python: >=3.6
License-File: License
Requires-Dist: pnu-libpnu >=1.3.0
Requires-Dist: pnu-vuxml >=1.2.1
